osmosis_on_premise_driver/__init__.py
osmosis_on_premise_driver/computing_plugin.py
osmosis_on_premise_driver/data_plugin.py
osmosis_on_premise_driver/log.py
osmosis_on_premise_driver-0.1.0.dist-info/LICENSE
osmosis_on_premise_driver-0.1.0.dist-info/METADATA
osmosis_on_premise_driver-0.1.0.dist-info/WHEEL
osmosis_on_premise_driver-0.1.0.dist-info/top_level.txt
osmosis_on_premise_driver-0.1.0.dist-info/RECORD
